hyo.soundspeed-2018.1.1-py3.6-nspkg.pth
hyo/sis/__init__.py
hyo/sis/__main__.py
hyo/sis/run.py
hyo/sis/gui/__init__.py
hyo/sis/gui/controlpanel.py
hyo/sis/gui/infoviewer.py
hyo/sis/gui/mainwin.py
hyo/sis/gui/media/favicon.png
hyo/sis/lib/__init__.py
hyo/sis/lib/kmbase.py
hyo/sis/lib/process.py
hyo/sis/lib/threads/__init__.py
hyo/sis/lib/threads/replaythread.py
hyo/sis/lib/threads/svpthread.py
hyo/soundspeed/__init__.py
hyo/soundspeed/soundspeed.py
hyo/soundspeed/appdirs/__init__.py
hyo/soundspeed/appdirs/appdirs.py
hyo/soundspeed/atlas/__init__.py
hyo/soundspeed/atlas/abstract.py
hyo/soundspeed/atlas/atlases.py
hyo/soundspeed/atlas/ftp.py
hyo/soundspeed/atlas/rtofs/__init__.py
hyo/soundspeed/atlas/rtofs/rtofs.py
hyo/soundspeed/atlas/woa09/__init__.py
hyo/soundspeed/atlas/woa09/woa09.py
hyo/soundspeed/atlas/woa13/__init__.py
hyo/soundspeed/atlas/woa13/woa13.py
hyo/soundspeed/base/__init__.py
hyo/soundspeed/base/basedb.py
hyo/soundspeed/base/gdal_aux.py
hyo/soundspeed/base/geodesy.py
hyo/soundspeed/base/helper.py
hyo/soundspeed/base/setup.py
hyo/soundspeed/base/setup_db.py
hyo/soundspeed/base/setup_sql.py
hyo/soundspeed/base/testing.py
hyo/soundspeed/base/callbacks/__init__.py
hyo/soundspeed/base/callbacks/abstract_callbacks.py
hyo/soundspeed/base/callbacks/cli_callbacks.py
hyo/soundspeed/base/callbacks/test_callbacks.py
hyo/soundspeed/base/progress/__init__.py
hyo/soundspeed/base/progress/abstract_progress.py
hyo/soundspeed/base/progress/cli_progress.py
hyo/soundspeed/client/__init__.py
hyo/soundspeed/client/client.py
hyo/soundspeed/client/clientlist.py
hyo/soundspeed/db/__init__.py
hyo/soundspeed/db/db.py
hyo/soundspeed/db/export.py
hyo/soundspeed/db/plot.py
hyo/soundspeed/db/point.py
hyo/soundspeed/formats/__init__.py
hyo/soundspeed/formats/abstract.py
hyo/soundspeed/formats/km.py
hyo/soundspeed/formats/readers/__init__.py
hyo/soundspeed/formats/readers/abstract.py
hyo/soundspeed/formats/readers/aml.py
hyo.soundspeed-2018.1.1.dist-info/DESCRIPTION.rst
hyo.soundspeed-2018.1.1.dist-info/METADATA
hyo.soundspeed-2018.1.1.dist-info/RECORD
hyo.soundspeed-2018.1.1.dist-info/WHEEL
hyo.soundspeed-2018.1.1.dist-info/entry_points.txt
hyo.soundspeed-2018.1.1.dist-info/metadata.json
hyo.soundspeed-2018.1.1.dist-info/namespace_packages.txt
hyo.soundspeed-2018.1.1.dist-info/top_level.txt
