Metadata-Version: 2.0
Name: hyo.soundspeed
Version: 2018.1.1
Summary: A library and an application to manage sound speed profiles.
Home-page: https://bitbucket.org/ccomjhc/hyo_soundspeed/
Author: Giuseppe Masetti(UNH,CCOM); Barry Gallagher(NOAA,OCS); Chen Zhang(NOAA,OCS); Matthew Sharr (NOAA,OCS)
Author-email: gmasetti@ccom.unh.edu, barry.gallagher@noaa.gov, chen.zhang@noaa.gov, matthew.sharr@noaa.gov
License: LGPLv2.1 or CCOM-UNH Industrial Associate license
Requires-Dist: basemap
Requires-Dist: gdal
Requires-Dist: matplotlib
Requires-Dist: netCDF4
Requires-Dist: numpy
Requires-Dist: pillow
Requires-Dist: pyproj
Requires-Dist: pyserial
